{"cameraMode":{"drawMode":0,"name":"Shaded","section":"Shading Mode"},"sceneLighting":false,"audioPlay":false,"sceneViewState":{"m_AlwaysRefresh":false,"showFog":true,"showSkybox":false,"showFlares":true,"showImageEffects":true,"showParticleSystems":true,"showVisualEffectGraphs":true,"m_FxEnabled":true},"in2DMode":false,"pivot":{"x":0.839459240436554,"y":0.1722710132598877,"z":0.941830575466156},"rotation":{"x":-0.2585679590702057,"y":0.13734422624111176,"z":-0.03801138326525688,"w":-0.9558207392692566},"size":1.8276405334472657,"orthographic":false}